misty2py/__init__.py
misty2py/action.py
misty2py/allowed_actions.json
misty2py/allowed_data.json
misty2py/allowed_infos.json
misty2py/basic_skills/__init__.py
misty2py/basic_skills/cancel_skills.py
misty2py/basic_skills/expression.py
misty2py/basic_skills/free_memory.py
misty2py/basic_skills/movement.py
misty2py/basic_skills/speak.py
misty2py/information.py
misty2py/misty_event.py
misty2py/response.py
misty2py/robot.py
misty2py/utils/__init__.py
misty2py/utils/base64.py
misty2py/utils/colours.py
misty2py/utils/env_loader.py
misty2py/utils/generators.py
misty2py/utils/status.py
misty2py/utils/utils.py
misty2py-5.0.3.dist-info/LICENSE
misty2py-5.0.3.dist-info/METADATA
misty2py-5.0.3.dist-info/WHEEL
misty2py-5.0.3.dist-info/RECORD
