Metadata-Version: 2.3
Name: misty2py
Version: 5.0.3
Summary: A Python package for Misty II development
License: MIT
Author: Chris 'Scar(R)ed' Vajdík
Author-email: chrisquackless@duck.com
Requires-Python: >=3.10
Classifier: Programming Language :: Python :: 3
Classifier: License :: OSI Approved :: MIT License
Classifier: Operating System :: OS Independent
Requires-Dist: python-dotenv (>=1.0.1,<2.0.0)
Requires-Dist: requests (>=2.32.3,<3.0.0)
Requires-Dist: websocket-client (>=1.8.0,<2.0.0)
Project-URL: Documentation, https://misty2py-documentation.onrender.com/
Project-URL: Repository, https://gitlab.com/scarred-libraries/misty2py
